pull_request_fixer/__init__.py
pull_request_fixer/_version.py
pull_request_fixer/cli.py
pull_request_fixer/exceptions.py
pull_request_fixer/file_fixer.py
pull_request_fixer/git_config.py
pull_request_fixer/github_client.py
pull_request_fixer/graphql_queries.py
pull_request_fixer/models.py
pull_request_fixer/pr_file_fixer.py
pull_request_fixer/pr_fixer.py
pull_request_fixer/pr_scanner.py
pull_request_fixer/progress_tracker.py
pull_request_fixer/py.typed
pull_request_fixer-0.1.1.dist-info/METADATA
pull_request_fixer-0.1.1.dist-info/WHEEL
pull_request_fixer-0.1.1.dist-info/entry_points.txt
pull_request_fixer-0.1.1.dist-info/licenses/LICENSE
pull_request_fixer-0.1.1.dist-info/RECORD
