Metadata-Version: 2.4
Name: pull-request-fixer
Version: 0.1.1
Summary: Pull request formatter and fixer with GitHub integration
Project-URL: Homepage, https://github.com/lfit/pull-request-fixer
Project-URL: Repository, https://github.com/lfit/pull-request-fixer.git
Project-URL: Bug Tracker, https://github.com/lfit/pull-request-fixer/issues
Author-email: The Linux Foundation <releng@linuxfoundation.org>
License: Apache-2.0
License-File: LICENSE
Keywords: formatter,github,pr,pre-commit,pull-request
Classifier: Development Status :: 4 - Beta
Classifier: Environment :: Console
Classifier: Intended Audience :: Developers
Classifier: License :: OSI Approved :: Apache Software License
Classifier: Operating System :: OS Independent
Classifier: Programming Language :: Python :: 3
Classifier: Programming Language :: Python :: 3.10
Classifier: Programming Language :: Python :: 3.11
Classifier: Programming Language :: Python :: 3.12
Classifier: Programming Language :: Python :: 3.13
Classifier: Topic :: Software Development :: Quality Assurance
Classifier: Topic :: Text Processing :: Markup :: Markdown
Requires-Python: <3.14,>=3.10
Requires-Dist: aiolimiter>=1.2.0
Requires-Dist: httpx[http2]>=0.28.0
Requires-Dist: pydantic>=2.10.3
Requires-Dist: rich>=13.9.4
Requires-Dist: tenacity>=9.0.0
Requires-Dist: typer>=0.15.0
Provides-Extra: dev
Requires-Dist: mypy>=1.13.0; extra == 'dev'
Requires-Dist: pre-commit>=4.0.1; extra == 'dev'
Requires-Dist: pytest-asyncio>=0.25.0; extra == 'dev'
Requires-Dist: pytest-cov>=6.0.0; extra == 'dev'
Requires-Dist: pytest-mock>=3.14.0; extra == 'dev'
Requires-Dist: pytest>=8.3.4; extra == 'dev'
Requires-Dist: ruff>=0.8.4; extra == 'dev'
